numbers_properties_pkg/__init__.py
numbers_properties_pkg/numbers_properties.py
smart_numbers_pkg_ganesh_patil-0.0.1.dist-info/LICENSE
smart_numbers_pkg_ganesh_patil-0.0.1.dist-info/METADATA
smart_numbers_pkg_ganesh_patil-0.0.1.dist-info/WHEEL
smart_numbers_pkg_ganesh_patil-0.0.1.dist-info/top_level.txt
smart_numbers_pkg_ganesh_patil-0.0.1.dist-info/RECORD
