Metadata-Version: 2.1
Name: smart-numbers-pkg-ganesh-patil
Version: 0.0.1
Summary: This is a test library created by Ganesh
Home-page: https://github.com/pypa/sampleproject
Author: Ganesh Patil
Author-email: ganeshpatil.1997@gmail.com
License: UNKNOWN
Platform: UNKNOWN
Classifier: Programming Language :: Python :: 3
Classifier: License :: OSI Approved :: MIT License
Classifier: Operating System :: OS Independent
Requires-Python: >=3.6
License-File: LICENSE
